{
  "pipeline_version": "1.0",
  "created_at": "2025-11-15T20:01:42.600491",
  "data_summary": {
    "total_accidents": 53213,
    "total_deaths": 4473,
    "total_injuries": 61040,
    "date_range": {
      "start": "2025-01-01",
      "end": "2025-09-30"
    },
    "geographic_coverage": {
      "states": 27,
      "highways": 112,
      "cities": 1790
    }
  },
  "output_files": {
    "accidents_detailed": {
      "rows": 53213,
      "columns": 99,
      "file": "accidents_detailed.csv"
    },
    "risk_time": {
      "rows": 71,
      "columns": 12
    },
    "risk_location": {
      "rows": 189,
      "columns": 12
    },
    "rankings": {
      "rows": 37,
      "columns": 7
    },
    "scenarios": {
      "rows": 6,
      "columns": 5
    },
    "daily": {
      "rows": 273,
      "columns": 10
    },
    "answers": {
      "rows": 4,
      "columns": 5
    },
    "map_points": {
      "rows": 53213,
      "columns": 20
    },
    "heatmap": {
      "rows": 439,
      "columns": 14
    },
    "segments": {
      "rows": 3255,
      "columns": 22
    }
  },
  "data_quality": {
    "completeness_pct": 100.0,
    "valid_coordinates_count": 0
  }
}